[
  {
    "type": "tree",
    "levels": 3,
    "points_per_branch": 10,
    "branches": [
      {
        "type": "trunk",
        "level": 0,
        "direction": [
          0,
          0,
          1
        ],
        "length": 10,
        "points": [
          [
            0.013715382379300319,
            -0.08664368481353661,
            0.017135395237966852
          ],
          [
            -0.008774263736692463,
            0.02725098286620979,
            1.0482991236699188
          ],
          [
            0.02036519825595491,
            -0.05973063039037751,
            1.9901395736745269
          ],
          [
            -0.07442601919623999,
            0.039769851348641784,
            3.095319856544411
          ],
          [
            -0.022688637142257165,
            0.0028214942681860622,
            4.034090029246121
          ],
          [
            0.11945036336360798,
            -0.025759133950611413,
            4.9507749293414225
          ],
          [
            -0.018665828392105854,
            0.0033751275173331645,
            5.996202955535819
          ],
          [
            -0.06844172558256388,
            0.02754926842592651,
            7.011794676538099
          ],
          [
            -0.05162992905312223,
            -0.1546679813710505,
            8.081498046992612
          ],
          [
            -0.0349357167124121,
            -0.029314313012320233,
            8.913210222283963
          ],
          [
            -0.014747173994703135,
            -0.09618276708236467,
            10.016405818373508
          ]
        ],
        "children": [
          {
            "type": "branch",
            "level": 1,
            "direction": [
              0.01764117276332757,
              -0.31677596238279954,
              0.9483363215020215
            ],
            "length": 41.10861266983639,
            "points": [
              [
                -0.014747173994703135,
                -0.09618276708236467,
                10.016405818373508
              ],
              [
                0.01142697047295102,
                -0.21410554217459468,
                11.444789566017487
              ],
              [
                0.03740191389682579,
                -0.3935884975674758,
                12.858516679685907
              ],
              [
                0.06297997127336583,
                -0.6332656595956953,
                14.246827842411985
              ],
              [
                0.08796647814148237,
                -0.9313129403351922,
                15.599157167962172
              ],
              [
                0.11217127209664368,
                -1.285462020013671,
                16.90521261361026
              ],
              [
                0.13541014004159677,
                -1.6930176102937158,
                18.155054308797027
              ],
              [
                0.1575062201592685,
                -2.1508779670445035,
                19.339170203547052
              ],
              [
                0.17829134793798537,
                -2.6555584964875174,
                20.448548460912562
              ],
              [
                0.19760733600494815,
                -3.2032182750592604,
                21.474746042494104
              ]
            ],
            "children": [
              {
                "type": "branch",
                "level": 2,
                "direction": [
                  0.007990645102808284,
                  -0.2265561001838758,
                  0.9739653397633382
                ],
                "length": 196.05763144595542,
                "points": [
                  [
                    0.19760733600494815,
                    -3.2032182750592604,
                    21.474746042494104
                  ],
                  [
                    0.30645489994671765,
                    -6.289337015647009,
                    27.574235988447292
                  ],
                  [
                    0.40519532485880505,
                    -9.088891408410541,
                    33.767878438106564
                  ],
                  [
                    0.493077136486531,
                    -11.580575154003775,
                    40.00853603260644
                  ],
                  [
                    0.5694315011789195,
                    -13.745425034602958,
                    46.248713599440705
                  ],
                  [
                    0.6336773161166354,
                    -15.56696523544463,
                    52.4409196194035
                  ],
                  [
                    0.6853256318553195,
                    -17.031332735724348,
                    58.5380276657267
                  ],
                  [
                    0.7239833735260943,
                    -18.12738281455571,
                    64.4936350646433
                  ],
                  [
                    0.7493563323726626,
                    -18.846773869025675,
                    70.26241604775346
                  ],
                  [
                    0.7612514048575911,
                    -19.18403089882954,
                    75.80046670849052
                  ]
                ],
                "children": []
              },
              {
                "type": "branch",
                "level": 2,
                "direction": [
                  -0.0186250619046568,
                  0.5280701791297604,
                  0.8489964622911632
                ],
                "length": 176.16494800344557,
                "points": [
                  [
                    0.19760733600494815,
                    -3.2032182750592604,
                    21.474746042494104
                  ],
                  [
                    0.28707356067564094,
                    -5.73982435614314,
                    27.081670955666446
                  ],
                  [
                    0.3508470232226222,
                    -7.547972106915946,
                    33.024854543159975
                  ],
                  [
                    0.3884423690884404,
                    -8.61390043120485,
                    39.25906558928148
                  ],
                  [
                    0.39957347499036566,
                    -8.92949697083688,
                    45.73685798365044
                  ],
                  [
                    0.38415562649133883,
                    -8.492359845583032,
                    52.40893181474772
                  ],
                  [
                    0.3423061627279893,
                    -7.305815932917117,
                    59.22450857201032
                  ],
                  [
                    0.2743435833889529,
                    -5.378895548469309,
                    66.13171760095774
                  ],
                  [
                    0.18078512473992736,
                    -2.7262637198716,
                    73.07799087019283
                  ],
                  [
                    0.062342823143373916,
                    0.631891422957473,
                    80.01046304586224
                  ]
                ],
                "children": []
              }
            ]
          },
          {
            "type": "branch",
            "level": 1,
            "direction": [
              0.00913174297818608,
              -0.8946850336559937,
              0.44660418921249917
            ],
            "length": 48.953281015485636,
            "points": [
              [
                -0.014747173994703135,
                -0.09618276708236467,
                10.016405818373508
              ],
              [
                0.01642172629769615,
                -0.31098479428185466,
                11.7128567698157
              ],
              [
                0.047353412438573717,
                -0.7472809542724077,
                13.382872099880174
              ],
              [
                0.07781247561933474,
                -1.4017507698336662,
                15.01374198352232
              ],
              [
                0.10756710397748845,
                -2.2694133304895345,
                16.593054516181454
              ],
              [
                0.13639084682489347,
                -3.343665200244444,
                18.108790175869064
              ],
              [
                0.1640643380742292,
                -4.616330673718539,
                19.54941329898871
              ],
              [
                0.19037696574737745,
                -6.077723998202268,
                20.903959873701435
              ],
              [
                0.21512847485974648,
                -7.716723088082889,
                22.162120982676083
              ],
              [
                0.23813049148162144,
                -9.520854170631699,
                23.31432126017491
              ]
            ],
            "children": [
              {
                "type": "branch",
                "level": 2,
                "direction": [
                  0.00860264698199829,
                  -0.6747366140783496,
                  0.7380084661350353
                ],
                "length": 198.88163821775117,
                "points": [
                  [
                    0.23813049148162144,
                    -9.520854170631699,
                    23.31432126017491
                  ],
                  [
                    0.3115895642287362,
                    -15.282514055367539,
                    27.173570673892876
                  ],
                  [
                    0.3824124559281741,
                    -20.837408757488173,
                    31.258585628265074
                  ],
                  [
                    0.45006016161007123,
                    -26.143262174173344,
                    35.53827669288927
                  ],
                  [
                    0.5140178413873868,
                    -31.15969355716019,
                    39.98007283461555
                  ],
                  [
                    0.5737987386983128,
                    -35.84852483462009,
                    44.550169302775544
                  ],
                  [
                    0.6289478848176199,
                    -40.17407116933784,
                    49.21378490374684
                  ],
                  [
                    0.6790455614433756,
                    -44.10341254186997,
                    53.935426706837994
                  ],
                  [
                    0.7237104950066535,
                    -47.606644291770294,
                    58.67916016692217
                  ],
                  [
                    0.7626027583936132,
                    -50.65710471011294,
                    63.40888260802359
                  ]
                ],
                "children": []
              },
              {
                "type": "branch",
                "level": 2,
                "direction": [
                  -0.0005698774986967288,
                  0.04469754654755692,
                  0.9990004026887405
                ],
                "length": 216.41748832113169,
                "points": [
                  [
                    0.23813049148162144,
                    -9.520854170631699,
                    23.31432126017491
                  ],
                  [
                    0.3158063621465059,
                    -15.613252716996037,
                    27.791482296537964
                  ],
                  [
                    0.38611030160071724,
                    -21.12744412377685,
                    33.067467690245735
                  ],
                  [
                    0.4485072544143298,
                    -26.021462064808745,
                    39.102124006725
                  ],
                  [
                    0.5025223421001216,
                    -30.258060108471618,
                    45.84952386758227
                  ],
                  [
                    0.5477444772256022,
                    -33.80499518552537,
                    53.25831548568499
                  ],
                  [
                    0.5838294920365947,
                    -36.635272978335664,
                    61.27211348326867
                  ],
                  [
                    0.61050275778166,
                    -38.72735336393075,
                    69.82992801870822
                  ],
                  [
                    0.62756127480272,
                    -40.06531434734359,
                    78.86662895603922
                  ],
                  [
                    0.6348752174850302,
                    -40.63897323760748,
                    88.31344154461938
                  ]
                ],
                "children": []
              }
            ]
          }
        ]
      }
    ]
  },
  {
    "type": "tree",
    "levels": 3,
    "points_per_branch": 10,
    "branches": [
      {
        "type": "trunk",
        "level": 0,
        "direction": [
          0,
          0,
          1
        ],
        "length": 10,
        "points": [
          [
            -0.05909741861383381,
            0.07603951191209217,
            0.006464109939977352
          ],
          [
            0.020556773761335956,
            0.02833987075567214,
            0.9343191888497397
          ],
          [
            0.051732374024795726,
            -0.130290577122902,
            2.1558511666676843
          ],
          [
            -0.07041132694723566,
            -0.000858068410843067,
            3.008468862876328
          ],
          [
            -0.04090681150893934,
            -0.046280076828126494,
            4.024850559960239
          ],
          [
            0.06845226313988281,
            0.12261865831791136,
            4.978040062000802
          ],
          [
            -0.04628070722496091,
            0.035320345702390815,
            6.009064385795559
          ],
          [
            -0.00982246805175663,
            -0.004282083658185872,
            6.99082102220236
          ],
          [
            -0.09578432337994841,
            -0.012224498192900807,
            8.026408380198955
          ],
          [
            0.06510267278504005,
            -0.10483848557582016,
            8.99617283862998
          ],
          [
            -0.05826506980859944,
            0.021931249803028588,
            10.058112076899041
          ]
        ],
        "children": [
          {
            "type": "branch",
            "level": 1,
            "direction": [
              -0.11068855564438897,
              -0.14325345961210928,
              0.983476735850178
            ],
            "length": 47.397341669533894,
            "points": [
              [
                -0.05826506980859944,
                0.021931249803028588,
                10.058112076899041
              ],
              [
                -0.24761664682323514,
                0.180686462880182,
                11.692310448417754
              ],
              [
                -0.4355271440031813,
                0.2665975948570373,
                13.3226231639687
              ],
              [
                -0.6205664490014381,
                0.2790108101446927,
                14.93664255937681
              ],
              [
                -0.8013263009771816,
                0.21783163667950312,
                16.52208497247147
              ],
              [
                -0.9764310083110938,
                0.08352568491253332,
                18.066884229172725
              ],
              [
                -1.1445479184492502,
                -0.12288489576711714,
                19.559283474361784
              ],
              [
                -1.304397560193734,
                -0.39982919620636226,
                20.987924648647457
              ],
              [
                -1.454763381251017,
                -0.7451995030553173,
                22.341934930056304
              ],
              [
                -1.594501006929488,
                -1.1563673397385679,
                23.61100948277305
              ]
            ],
            "children": [
              {
                "type": "branch",
                "level": 2,
                "direction": [
                  -0.10062946492320732,
                  -0.5423136135351673,
                  0.8341280809106587
                ],
                "length": 209.07010346595763,
                "points": [
                  [
                    -1.594501006929488,
                    -1.1563673397385679,
                    23.61100948277305
                  ],
                  [
                    -2.353828839934865,
                    -3.5420030830680975,
                    30.45806028724556
                  ],
                  [
                    -3.107377729636389,
                    -6.2122199452803955,
                    37.15491697113285
                  ],
                  [
                    -3.8494127139781735,
                    -9.146695963732995,
                    43.65061241139791
                  ],
                  [
                    -4.5742864586764025,
                    -12.323098004040412,
                    49.89571044353218
                  ],
                  [
                    -5.276482236843188,
                    -15.717251728711922,
                    55.842682100617836
                  ],
                  [
                    -5.9506559146092775,
                    -19.303325578456704,
                    61.44626733746477
                  ],
                  [
                    -6.591676623209676,
                    -23.05402736594763,
                    66.66381948688333
                  ],
                  [
                    -7.194665807993047,
                    -26.940811985846217,
                    71.45562982657228
                  ],
                  [
                    -7.755034357168366,
                    -30.934098660290324,
                    75.78522978647244
                  ]
                ],
                "children": []
              },
              {
                "type": "branch",
                "level": 2,
                "direction": [
                  -0.05208964404120426,
                  -0.9771338489697441,
                  0.2061458468687496
                ],
                "length": 221.4606327934807,
                "points": [
                  [
                    -1.594501006929488,
                    -1.1563673397385679,
                    23.61100948277305
                  ],
                  [
                    -2.398830366351527,
                    -4.004066622593878,
                    30.759953545235234
                  ],
                  [
                    -3.197038293681019,
                    -7.792130060463235,
                    37.54279922023871
                  ],
                  [
                    -3.9830499446198617,
                    -12.491728203289188,
                    43.90792495660253
                  ],
                  [
                    -4.7508832958976,
                    -18.067094271509912,
                    49.80688830410493
                  ],
                  [
                    -5.4946946720805565,
                    -24.475796362848175,
                    55.19479458977998
                  ],
                  [
                    -6.208823219470389,
                    -31.669060384708736,
                    60.03063859348692
                  ],
                  [
                    -6.887833988618858,
                    -39.59214125447371,
                    64.2776166223951
                  ],
                  [
                    -7.526559297574828,
                    -48.18473954263713,
                    67.90340660930909
                  ],
                  [
                    -8.12013806106426,
                    -57.381460387873354,
                    70.88041410311664
                  ]
                ],
                "children": []
              }
            ]
          },
          {
            "type": "branch",
            "level": 1,
            "direction": [
              -0.05729661255131598,
              -0.8010432840249808,
              0.595857999282227
            ],
            "length": 47.57845110984954,
            "points": [
              [
                -0.05826506980859944,
                0.021931249803028588,
                10.058112076899041
              ],
              [
                -0.2483401759691334,
                0.10938349558172276,
                11.707139121871375
              ],
              [
                -0.4369686958012987,
                -0.019558578118929193,
                13.36936884554628
              ],
              [
                -0.6227150523721582,
                -0.36391364426070727,
                15.03215067604484
              ],
              [
                -0.804165603751491,
                -0.9210609528630034,
                16.682829839621835
              ],
              [
                -0.9799394016804621,
                -1.6867602764926124,
                18.308843671135122
              ],
              [
                -1.1486987014217105,
                -2.655184180954814,
                19.897817223512885
              ],
              [
                -1.3091591428045548,
                -3.8189623755863167,
                21.43765744857307
              ],
              [
                -1.4600995249814077,
                -5.1692378056174855,
                22.916645232422017
              ],
              [
                -1.6003711005036088,
                -6.695734059707183,
                24.323524584987396
              ]
            ],
            "children": [
              {
                "type": "branch",
                "level": 2,
                "direction": [
                  -0.04910551232867179,
                  -0.534387528947438,
                  0.8438119562819609
                ],
                "length": 206.56950032269353,
                "points": [
                  [
                    -1.6003711005036088,
                    -6.695734059707183,
                    24.323524584987396
                  ],
                  [
                    -2.076143902474874,
                    -11.87330048614223,
                    29.308760880820653
                  ],
                  [
                    -2.5288413986307883,
                    -16.799751404977286,
                    34.48770758295574
                  ],
                  [
                    -2.955018287679384,
                    -21.43759355004763,
                    39.82094977985588
                  ],
                  [
                    -3.3514311061623587,
                    -25.751530142223615,
                    45.26789827810299
                  ],
                  [
                    -3.7150629131704536,
                    -29.708729519212653,
                    50.78709851066798
                  ],
                  [
                    -4.043146251085449,
                    -33.27907500433354,
                    56.336546031196804
                  ],
                  [
                    -4.333184207603675,
                    -36.43539411261097,
                    61.87400619321022
                  ],
                  [
                    -4.582969418746322,
                    -39.15366534979336,
                    67.35733558126543
                  ],
                  [
                    -4.790600868232162,
                    -41.4132010304287,
                    72.74480274779455
                  ]
                ],
                "children": []
              },
              {
                "type": "branch",
                "level": 2,
                "direction": [
                  0.01987540855380919,
                  0.21629283475959915,
                  0.9761262099577472
                ],
                "length": 207.5269221696427,
                "points": [
                  [
                    -1.6003711005036088,
                    -6.695734059707183,
                    24.323524584987396
                  ],
                  [
                    -2.0588044894305666,
                    -11.684605456791394,
                    29.564591516659284
                  ],
                  [
                    -2.4551152555119624,
                    -15.997431470376164,
                    35.46394497295328
                  ],
                  [
                    -2.786287234518935,
                    -19.601388890342577,
                    41.976687311939955
                  ],
                  [
                    -3.0498000077241327,
                    -22.469049424595696,
                    49.05325263191829
                  ],
                  [
                    -3.243648083810099,
                    -24.578588444929075,
                    56.6397839978563
                  ],
                  [
                    -3.3663561618691547,
                    -25.913951085623502,
                    64.67854332518628
                  ],
                  [
                    -3.4169903593341044,
                    -26.464974430669272,
                    73.1083508014917
                  ],
                  [
                    -3.395165319388476,
                    -26.227464859693598,
                    81.86505050182089
                  ],
                  [
                    -3.3010471437645776,
                    -25.203229963943826,
                    90.88199865401457
                  ]
                ],
                "children": []
              }
            ]
          }
        ]
      }
    ]
  },
  {
    "type": "tree",
    "levels": 3,
    "points_per_branch": 10,
    "branches": [
      {
        "type": "trunk",
        "level": 0,
        "direction": [
          0,
          0,
          1
        ],
        "length": 10,
        "points": [
          [
            0.024254244055049015,
            0.020564694890450392,
            -0.02000525828936406
          ],
          [
            0.030484182771277252,
            0.05216766586892509,
            1.0452493624684647
          ],
          [
            -0.05388650452487884,
            -0.004728763173639303,
            1.9992665260157405
          ],
          [
            -0.06770681770919972,
            0.01058675916352956,
            2.9862173166426
          ],
          [
            0.0015269721509553042,
            0.019545317650195612,
            4.04456996484596
          ],
          [
            -0.11562898719001916,
            -0.023439813541670573,
            4.885709271725557
          ],
          [
            -0.048460752135803316,
            0.02989218013919458,
            5.926587547492785
          ],
          [
            0.09147284564546701,
            -0.001988248533133041,
            7.033554346436376
          ],
          [
            -0.013483920416911334,
            0.08067113639836641,
            7.968132335792962
          ],
          [
            0.03853718699746856,
            -0.024116233568654902,
            8.99925675274644
          ],
          [
            -0.09904265086669622,
            -0.019390751918122007,
            9.943820725016451
          ]
        ],
        "children": [
          {
            "type": "branch",
            "level": 1,
            "direction": [
              -0.13922051657930073,
              -0.25403397191359417,
              0.9571229747933104
            ],
            "length": 45.919731322354025,
            "points": [
              [
                -0.09904265086669622,
                -0.019390751918122007,
                9.943820725016451
              ],
              [
                -0.32977835401514466,
                -0.04641287842339259,
                11.528127622225325
              ],
              [
                -0.5587580191406066,
                -0.14312385205965297,
                13.10072665678822
              ],
              [
                -0.7842389727297754,
                -0.3087876439218471,
                14.649649400490857
              ],
              [
                -1.0045051685767152,
                -0.5421434525233726,
                16.16310761598853
              ],
              [
                -1.2178802479306654,
                -0.8414152992566828,
                17.629582972410255
              ],
              [
                -1.4227402975983465,
                -1.204325544662853,
                19.03791470681162
              ],
              [
                -1.6175262089039082,
                -1.6281122226431477,
                20.37738456431989
              ],
              [
                -1.8007555434473657,
                -2.1095500606887425,
                21.637798370525402
              ],
              [
                -1.9710338153559468,
                -2.6449750261519958,
                22.809563615304285
              ]
            ],
            "children": [
              {
                "type": "branch",
                "level": 2,
                "direction": [
                  -0.12656851476783892,
                  -0.6333909788002606,
                  0.7634109503039049
                ],
                "length": 187.7833021777454,
                "points": [
                  [
                    -1.9710338153559468,
                    -2.6449750261519958,
                    22.809563615304285
                  ],
                  [
                    -2.8288512668123023,
                    -5.472293188305754,
                    28.653214688399604
                  ],
                  [
                    -3.6801402094987363,
                    -8.538067866428843,
                    34.33359979722114
                  ],
                  [
                    -4.518421820539087,
                    -11.818966664055374,
                    39.807487781180455
                  ],
                  [
                    -5.337316270705062,
                    -15.290019960274558,
                    45.03321904749569
                  ],
                  [
                    -6.130591278768911,
                    -18.924810943622887,
                    49.97102262584738
                  ],
                  [
                    -6.892209542926719,
                    -22.695676659970264,
                    54.583318849476925
                  ],
                  [
                    -7.616374688310567,
                    -26.573918544304327,
                    58.83500535914193
                  ],
                  [
                    -8.297575380901213,
                    -30.530020834138814,
                    62.69372425326533
                  ],
                  [
                    -8.930627272107818,
                    -34.53387520228821,
                    66.13010835110467
                  ]
                ],
                "children": []
              },
              {
                "type": "branch",
                "level": 2,
                "direction": [
                  -0.06551668426451275,
                  -0.9937001946908938,
                  0.09092572328150028
                ],
                "length": 224.85520657286324,
                "points": [
                  [
                    -1.9710338153559468,
                    -2.6449750261519958,
                    22.809563615304285
                  ],
                  [
                    -2.998200331292767,
                    -6.341756020717089,
                    29.6646156784452
                  ],
                  [
                    -4.017549489823209,
                    -10.944295749141755,
                    36.04076452632992
                  ],
                  [
                    -5.021323428351005,
                    -16.417566105003196,
                    41.88948381620213
                  ],
                  [
                    -6.0018828211086825,
                    -22.719912196042323,
                    47.16626126271262
                  ],
                  [
                    -6.951765019039408,
                    -29.803369363045718,
                    51.830937403288104
                  ],
                  [
                    -7.863740845062374,
                    -37.614028219864075,
                    55.84801123589034
                  ],
                  [
                    -8.73086961247549,
                    -46.09244493639228,
                    59.186910403077746
                  ],
                  [
                    -9.54655194777207,
                    -55.17409364200957,
                    61.82222386610557
                  ],
                  [
                    -10.304580015858054,
                    -64.78985750641674,
                    63.73389529827442
                  ]
                ],
                "children": []
              }
            ]
          },
          {
            "type": "branch",
            "level": 1,
            "direction": [
              -0.07206584231946855,
              -0.8635393068567614,
              0.4991055798968086
            ],
            "length": 41.07871212088586,
            "points": [
              [
                -0.09904265086669622,
                -0.019390751918122007,
                9.943820725016451
              ],
              [
                -0.3054533865721811,
                -0.1060900892284321,
                11.361417236115464
              ],
              [
                -0.5102932119447373,
                -0.37970752682479186,
                12.769163400065993
              ],
              [
                -0.7120031722276117,
                -0.8381606707923626,
                14.156345418540004
              ],
              [
                -0.9090481328272473,
                -1.4779604158839783,
                15.512405998773504
              ],
              [
                -1.0999284626144807,
                -2.294237499717844,
                16.827024700939152
              ],
              [
                -1.2831914470229369,
                -3.280779560804399,
                18.090196482924988
              ],
              [
                -1.457442344084052,
                -4.4300784183683986,
                19.292307844746126
              ],
              [
                -1.6213549992556224,
                -5.733387214138154,
                20.42420999308443
              ],
              [
                -1.7736819382586255,
                -7.180786981218486,
                21.47728846912983
              ]
            ],
            "children": [
              {
                "type": "branch",
                "level": 2,
                "direction": [
                  -0.06602540460141973,
                  -0.6273687101373158,
                  0.7759182608289739
                ],
                "length": 192.09979847039477,
                "points": [
                  [
                    -1.7736819382586255,
                    -7.180786981218486,
                    21.47728846912983
                  ],
                  [
                    -2.3325839144987253,
                    -12.491433906347794,
                    25.52159065788929
                  ],
                  [
                    -2.869292247026619,
                    -17.591198403523382,
                    29.772003533460875
                  ],
                  [
                    -3.3797222613584177,
                    -22.44126818559976,
                    34.19617888739202
                  ],
                  [
                    -3.859989276878988,
                    -27.004731292983113,
                    38.7604460738492
                  ],
                  [
                    -4.306438171607064,
                    -31.246857015931894,
                    43.43006826356359
                  ],
                  [
                    -4.7156711998805525,
                    -35.13536021622892,
                    48.16950681207649
                  ],
                  [
                    -5.084573851252635,
                    -38.640647036577505,
                    52.94269173028249
                  ],
                  [
                    -5.410338553796858,
                    -41.736040127724735,
                    57.713296198826185
                  ],
                  [
                    -5.690486041424755,
                    -44.39798167919756,
                    62.44501303713222
                  ]
                ],
                "children": []
              },
              {
                "type": "branch",
                "level": 2,
                "direction": [
                  0.010737502444196093,
                  0.10202698641799351,
                  0.9947236802668988
                ],
                "length": 187.04643582773875,
                "points": [
                  [
                    -1.7736819382586255,
                    -7.180786981218486,
                    21.47728846912983
                  ],
                  [
                    -2.300413349460885,
                    -12.185751479802779,
                    25.645860204219858
                  ],
                  [
                    -2.770731619700927,
                    -16.654682315376387,
                    30.4746825448195
                  ],
                  [
                    -3.181057342956289,
                    -20.553568225866403,
                    35.927005237194145
                  ],
                  [
                    -3.5282676927115526,
                    -23.852736335282298,
                    41.96133281345237
                  ],
                  [
                    -3.809720188553737,
                    -26.527077982219254,
                    48.53174039711226
                  ],
                  [
                    -4.0232728070438215,
                    -28.556239811932446,
                    55.58822321914154
                  ],
                  [
                    -4.167300283808499,
                    -29.924778677656334,
                    63.0770771844438
                  ],
                  [
                    -4.240706482783422,
                    -30.622279172276407,
                    70.94130759244942
                  ],
                  [
                    -4.242932738470519,
                    -30.64343289586631,
                    79.1210629012013
                  ]
                ],
                "children": []
              }
            ]
          }
        ]
      }
    ]
  },
  {
    "type": "tree",
    "levels": 3,
    "points_per_branch": 10,
    "branches": [
      {
        "type": "trunk",
        "level": 0,
        "direction": [
          0,
          0,
          1
        ],
        "length": 10,
        "points": [
          [
            -0.042915840030101744,
            -0.02625762440670647,
            0.058202258902630324
          ],
          [
            -0.03661283559558228,
            0.08177064472656796,
            0.9661759125429763
          ],
          [
            0.05872749404982228,
            -0.0710556159782772,
            2.050280735582002
          ],
          [
            -0.07199838766689709,
            0.026153832861846124,
            3.0214729952665835
          ],
          [
            0.007115577982490154,
            -0.0036329207163823176,
            4.026351074605942
          ],
          [
            0.03470451262133492,
            0.028971043387199937,
            5.014567683639374
          ],
          [
            0.027916660381550686,
            -0.012065509539432995,
            5.960795471914452
          ],
          [
            0.043382639803482025,
            -0.010849356071546093,
            6.980887183292233
          ],
          [
            -0.04085674231752014,
            -0.07920907232151107,
            8.050404701338488
          ],
          [
            0.014347221018633234,
            -0.0261807200668068,
            8.920294434918915
          ],
          [
            0.03406159651589208,
            0.04019397735174624,
            10.069021774413327
          ]
        ],
        "children": [
          {
            "type": "branch",
            "level": 1,
            "direction": [
              0.016547117044420415,
              -0.2026769531984258,
              0.9791058398149413
            ],
            "length": 43.51466163422123,
            "points": [
              [
                0.03406159651589208,
                0.04019397735174624,
                10.069021774413327
              ],
              [
                0.060049435736585,
                0.09462814050407085,
                11.585204880566922
              ],
              [
                0.08583949180892209,
                0.08252374783437993,
                13.093669649528199
              ],
              [
                0.11123548683373125,
                0.003972921079723524,
                14.582935753569434
              ],
              [
                0.13604414195435263,
                -0.1404265205380108,
                16.041668978395414
              ],
              [
                0.16007664832544277,
                -0.3495756100773458,
                17.458767483358013
              ],
              [
                0.18315010406229354,
                -0.6218825966792119,
                18.823446293166988
              ],
              [
                0.20508890623461407,
                -0.9552750597521172,
                20.1253193780641
              ],
              [
                0.22572608731086202,
                -1.3472156813442027,
                21.35447869778082
              ],
              [
                0.24490458588197658,
                -1.7947215566649344,
                22.50156960770742
              ]
            ],
            "children": [
              {
                "type": "branch",
                "level": 2,
                "direction": [
                  0.015043357685064554,
                  -0.592137570544968,
                  0.805696465760315
                ],
                "length": 175.34649466194836,
                "points": [
                  [
                    0.24490458588197658,
                    -1.7947215566649344,
                    22.50156960770742
                  ],
                  [
                    0.3401083438834955,
                    -4.140503649191938,
                    28.147328659679754
                  ],
                  [
                    0.43458754380102205,
                    -6.7170798593630865,
                    33.65311733333957
                  ],
                  [
                    0.5276231418750832,
                    -9.50484088643972,
                    38.97703325239423
                  ],
                  [
                    0.6185070810279053,
                    -12.482570185709656,
                    44.07855820203139
                  ],
                  [
                    0.7065476796053126,
                    -15.627605439203348,
                    48.918866496999335
                  ],
                  [
                    0.791074895491764,
                    -18.916011029617486,
                    53.461120468515304
                  ],
                  [
                    0.8714454255354355,
                    -22.322760204815452,
                    57.67075082116812
                  ],
                  [
                    0.9470476014736414,
                    -25.821925546522582,
                    61.51571972612979
                  ],
                  [
                    1.0173060450976505,
                    -29.38687629363469,
                    64.96676464837788
                  ]
                ],
                "children": []
              },
              {
                "type": "branch",
                "level": 2,
                "direction": [
                  0.0077870149423681515,
                  -0.9885031659057049,
                  0.15099951454453758
                ],
                "length": 188.4220679609254,
                "points": [
                  [
                    0.24490458588197658,
                    -1.7947215566649344,
                    22.50156960770742
                  ],
                  [
                    0.34720768007773695,
                    -4.582616938524945,
                    28.464096206129987
                  ],
                  [
                    0.44873218595437037,
                    -8.150860303533559,
                    34.068535689049035
                  ],
                  [
                    0.548705440719983,
                    -12.472295165118796,
                    39.27223488794647
                  ],
                  [
                    0.6463665875403067,
                    -17.514032794630292,
                    44.03559050983921
                  ],
                  [
                    0.7409723661186264,
                    -23.237702524423057,
                    48.32235054225187
                  ],
                  [
                    0.8318027693554297,
                    -29.599743771807066,
                    52.09989015292132
                  ],
                  [
                    0.918166523037188,
                    -36.55173756138423,
                    55.33945998446959
                  ],
                  [
                    0.9994063468505225,
                    -44.040775022687214,
                    58.016404954372845
                  ],
                  [
                    1.0749039566822673,
                    -52.00986005863106,
                    60.11035189502658
                  ]
                ],
                "children": []
              }
            ]
          },
          {
            "type": "branch",
            "level": 1,
            "direction": [
              0.008565418065273075,
              -0.8357451384556001,
              0.5490507236687672
            ],
            "length": 48.67047925083132,
            "points": [
              [
                0.03406159651589208,
                0.04019397735174624,
                10.069021774413327
              ],
              [
                0.06312859467381793,
                0.02711876274401971,
                11.769122670872953
              ],
              [
                0.09197437542462861,
                -0.20773390627922522,
                13.469105061892908
              ],
              [
                0.12037940495925183,
                -0.6625766590987977,
                15.156031055000103
              ],
              [
                0.14812750385150333,
                -1.3339478677241825,
                16.817062124793228
              ],
              [
                0.17500749231405285,
                -2.216737991872722,
                18.439556821873175
              ],
              [
                0.20081479740411962,
                -3.304228465656388,
                20.011166981906072
              ],
              [
                0.2253530099470914,
                -4.588142829924994,
                21.519931702609924
              ],
              [
                0.24843537932893828,
                -6.058709721117761,
                22.954368373443124
              ],
              [
                0.26988623478114876,
                -7.704737237240146,
                24.303560065204085
              ]
            ],
            "children": [
              {
                "type": "branch",
                "level": 2,
                "direction": [
                  0.00759699979573164,
                  -0.5829544062524465,
                  0.8124693506988194
                ],
                "length": 236.2296232558811,
                "points": [
                  [
                    0.26988623478114876,
                    -7.704737237240146,
                    24.303560065204085
                  ],
                  [
                    0.35140098169720535,
                    -13.959756608961982,
                    29.663036840024187
                  ],
                  [
                    0.4293252607987371,
                    -19.939262081873284,
                    35.259823786119796
                  ],
                  [
                    0.5030660212698154,
                    -25.59774600880108,
                    41.051325975398754
                  ],
                  [
                    0.5720620513973664,
                    -30.89214391037545,
                    46.993466579196024
                  ],
                  [
                    0.6357882497311778,
                    -35.78216222172053,
                    53.04102231955412
                  ],
                  [
                    0.6937596214229983,
                    -40.230584950813224,
                    59.14796764567491
                  ],
                  [
                    0.7455349693301823,
                    -44.203556914654044,
                    65.26782501615222
                  ],
                  [
                    0.7907202517923458,
                    -47.67084139765209,
                    71.35401862112579
                  ],
                  [
                    0.8289715815263328,
                    -50.60605027128817,
                    77.36022885231762
                  ]
                ],
                "children": []
              },
              {
                "type": "branch",
                "level": 2,
                "direction": [
                  -0.002114330852896737,
                  0.16224279585530021,
                  0.9867486026329604
                ],
                "length": 217.06850360344933,
                "points": [
                  [
                    0.26988623478114876,
                    -7.704737237240146,
                    24.303560065204085
                  ],
                  [
                    0.3420599554615774,
                    -13.242974649057427,
                    29.483859326988
                  ],
                  [
                    0.40549684894562216,
                    -18.110793205044303,
                    35.391358735386675
                  ],
                  [
                    0.459714122169626,
                    -22.27114586672052,
                    41.981098652856495
                  ],
                  [
                    0.5042991489470694,
                    -25.692369838241095,
                    49.202927179631786
                  ],
                  [
                    0.538912610303001,
                    -28.34842753939123,
                    57.00188183996451
                  ],
                  [
                    0.5632910768963226,
                    -30.219104767293707,
                    65.31860787975192
                  ],
                  [
                    0.5772490138761386,
                    -31.290164538698377,
                    74.0898099920548
                  ],
                  [
                    0.5806801929139996,
                    -31.55345544202128,
                    83.24873403260185
                  ],
                  [
                    0.5735585006656254,
                    -31.006973674508764,
                    92.72567505913499
                  ]
                ],
                "children": []
              }
            ]
          }
        ]
      }
    ]
  },
  {
    "type": "tree",
    "levels": 3,
    "points_per_branch": 10,
    "branches": [
      {
        "type": "trunk",
        "level": 0,
        "direction": [
          0,
          0,
          1
        ],
        "length": 10,
        "points": [
          [
            0.09568472583070885,
            -0.03965123234528205,
            -0.05915233437518677
          ],
          [
            0.04343848652029868,
            0.05234651662887557,
            1.0072230259737458
          ],
          [
            -0.004203531653382916,
            -0.026004652052346935,
            2.0146882477336443
          ],
          [
            -0.054837532379347166,
            -0.005181992456277472,
            3.093978201270091
          ],
          [
            0.10838840978167863,
            -0.04040878608939774,
            3.9744772053319974
          ],
          [
            0.008527740811703242,
            -0.03501501124086029,
            4.9206090246219185
          ],
          [
            -0.05665853607134236,
            -0.09937347915365558,
            5.998082937944068
          ],
          [
            0.011817944691729015,
            -0.01838886778362594,
            6.964490025063834
          ],
          [
            -0.011128745704309946,
            -0.031607269658360436,
            8.027392608412304
          ],
          [
            -0.018134253342484603,
            0.004757499093499566,
            8.92883301642629
          ],
          [
            -0.011055618564763947,
            0.07226430929608164,
            9.95751199308987
          ]
        ],
        "children": [
          {
            "type": "branch",
            "level": 1,
            "direction": [
              0.006632389468981101,
              -0.1950124196054437,
              0.9807783478490755
            ],
            "length": 42.3953201675635,
            "points": [
              [
                -0.011055618564763947,
                0.07226430929608164,
                9.95751199308987
              ],
              [
                -0.0009071581512258165,
                0.1368509780774118,
                11.43441600009477
              ],
              [
                0.009164066350757349,
                0.13655381346142642,
                12.904305604347106
              ],
              [
                0.019081406841553843,
                0.07137507705028756,
                14.355994058414915
              ],
              [
                0.028769386371774786,
                -0.058189181615920293,
                15.778433136609278
              ],
              [
                0.03815427356743323,
                -0.2511529002957093,
                17.160797218652945
              ],
              [
                0.047164643770220366,
                -0.5060475085752453,
                18.492565679187305
              ],
              [
                0.05573192262228272,
                -0.8209331045759509,
                19.763602956083915
              ],
              [
                0.06379090795849171,
                -1.1934132187791384,
                20.96423568819229
              ],
              [
                0.07128026603429037,
                -1.620653052606078,
                22.085326335459236
              ]
            ],
            "children": [
              {
                "type": "branch",
                "level": 2,
                "direction": [
                  0.006029655003992421,
                  -0.585821144476919,
                  0.8104179353545217
                ],
                "length": 173.41484887514954,
                "points": [
                  [
                    0.07128026603429037,
                    -1.620653052606078,
                    22.085326335459236
                  ],
                  [
                    0.1090193163660572,
                    -3.896851702781489,
                    27.687529185512773
                  ],
                  [
                    0.14647114973733766,
                    -6.402381397066213,
                    33.15309765786925
                  ],
                  [
                    0.18335073508214103,
                    -9.118173541606543,
                    38.44043547625357
                  ],
                  [
                    0.21937739648749088,
                    -12.023559318342404,
                    43.50930280728596
                  ],
                  [
                    0.2542769493065996,
                    -15.09642698719294,
                    48.32112250991149
                  ],
                  [
                    0.28778378686958755,
                    -18.313390169749958,
                    52.83927373073699
                  ],
                  [
                    0.31964290191061884,
                    -21.649965833738733,
                    57.02937061083772
                  ],
                  [
                    0.3496118273271715,
                    -25.080760623676838,
                    60.85952398290638
                  ],
                  [
                    0.3774624815010937,
                    -28.57966411964231,
                    64.30058406707177
                  ]
                ],
                "children": []
              },
              {
                "type": "branch",
                "level": 2,
                "direction": [
                  0.0031211791008619095,
                  -0.9873038265373753,
                  0.15881250689311888
                ],
                "length": 187.78071070567083,
                "points": [
                  [
                    0.07128026603429037,
                    -1.620653052606078,
                    22.085326335459236
                  ],
                  [
                    0.11214565754270912,
                    -4.352501687429852,
                    28.04983620719128
                  ],
                  [
                    0.15270003874655078,
                    -7.864821449474752,
                    33.66359713717764
                  ],
                  [
                    0.1926347663174492,
                    -12.130881464554939,
                    38.883885015059604
                  ],
                  [
                    0.23164591286534209,
                    -17.1182144400382,
                    43.67097029799048
                  ],
                  [
                    0.26943658000942566,
                    -22.788863760547137,
                    47.988420376446044
                  ],
                  [
                    0.30571915795410465,
                    -29.099672360720966,
                    51.8033768483816
                  ],
                  [
                    0.3402175143732007,
                    -36.002611176541976,
                    55.08680559151205
                  ],
                  [
                    0.37266909594368713,
                    -43.44514467551335,
                    57.813717730513666
                  ],
                  [
                    0.40282692653501206,
                    -51.3706306837833,
                    59.9633598174541
                  ]
                ],
                "children": []
              }
            ]
          },
          {
            "type": "branch",
            "level": 1,
            "direction": [
              0.0034331774182194074,
              -0.8314254089795627,
              0.5556257756763828
            ],
            "length": 47.46212833386706,
            "points": [
              [
                -0.011055618564763947,
                0.07226430929608164,
                9.95751199308987
              ],
              [
                0.00030571869214957373,
                0.07248191911189591,
                11.615656555006936
              ],
              [
                0.011580589312374982,
                -0.14356621809499037,
                13.275373914494047
              ],
              [
                0.02268318472253935,
                -0.5742358455469957,
                14.92403262028077
              ],
              [
                0.03352900746764092,
                -1.216249307333784,
                16.54908538412872
              ],
              [
                0.04403551428770265,
                -2.064720493352832,
                18.138164573271332
              ],
              [
                0.054122744321821584,
                -3.1131920255576175,
                19.67917633556697
              ],
              [
                0.06371392765860208,
                -4.353684402503651,
                21.160392641016237
              ],
              [
                0.07273606960153638,
                -5.776756728172593,
                22.5705405391518
              ],
              [
                0.08112050620272053,
                -7.371578562891536,
                23.898887952998265
              ]
            ],
            "children": [
              {
                "type": "branch",
                "level": 2,
                "direction": [
                  0.0030311064359976724,
                  -0.5765533162721364,
                  0.8170539063546394
                ],
                "length": 221.23989865108948,
                "points": [
                  [
                    0.08112050620272053,
                    -7.371578562891536,
                    23.898887952998265
                  ],
                  [
                    0.11171085970455297,
                    -13.190235917829764,
                    28.964452817995998
                  ],
                  [
                    0.14093537479521245,
                    -18.749094192108373,
                    34.25022212491888
                  ],
                  [
                    0.1685716352686144,
                    -24.00584711772972,
                    39.71596797770644
                  ],
                  [
                    0.1944093124953259,
                    -28.920487630815614,
                    45.3200927501114
                  ],
                  [
                    0.21825176615043557,
                    -33.4556123495204,
                    51.0199456687527
                  ],
                  [
                    0.23991754076516095,
                    -37.576706236351555,
                    56.77214741125417
                  ],
                  [
                    0.2592417467125316,
                    -41.25240527844577,
                    62.53292024908103
                  ],
                  [
                    0.2760773151170134,
                    -44.45473518664495,
                    68.25842122248766
                  ],
                  [
                    0.2902961171374542,
                    -47.15932429672805,
                    73.90507581191443
                  ]
                ],
                "children": []
              },
              {
                "type": "branch",
                "level": 2,
                "direction": [
                  -0.0008940101938632134,
                  0.17005161413385833,
                  0.9854347514048014
                ],
                "length": 226.2007390662095,
                "points": [
                  [
                    0.08112050620272053,
                    -7.371578562891536,
                    23.898887952998265
                  ],
                  [
                    0.11123835107189098,
                    -13.10035902802704,
                    29.342595998630983
                  ],
                  [
                    0.13765168162438024,
                    -18.124495806258448,
                    35.538549697673005
                  ],
                  [
                    0.16015947646587894,
                    -22.4057521830467,
                    42.439594101255466
                  ],
                  [
                    0.17859043768706506,
                    -25.911545212271154,
                    49.993208094502585
                  ],
                  [
                    0.19280429454412673,
                    -28.61519369212369,
                    58.14190411392893
                  ],
                  [
                    0.20269287100382033,
                    -30.496121225165062,
                    66.82366566250944
                  ],
                  [
                    0.20818090902840183,
                    -31.540012817133714,
                    75.97241929266852
                  ],
                  [
                    0.20922664133473623,
                    -31.738923822695803,
                    85.51853746511215
                  ],
                  [
                    0.205822109268542,
                    -31.091340408993254,
                    95.38936845644429
                  ]
                ],
                "children": []
              }
            ]
          }
        ]
      }
    ]
  }
]